mneflow/__init__.py
mneflow/data.py
mneflow/layers.py
mneflow/models.py
mneflow/utils.py
mneflow-0.5.10.dist-info/LICENSE.md
mneflow-0.5.10.dist-info/METADATA
mneflow-0.5.10.dist-info/WHEEL
mneflow-0.5.10.dist-info/top_level.txt
mneflow-0.5.10.dist-info/RECORD
