Metadata-Version: 2.1
Name: mneflow
Version: 0.5.10
Summary: Neural networks for MEG and EEG data
Home-page: https://github.com/zubara/mneflow
Download-URL: https://github.com/zubara/mneflow/archive/master.zip
Maintainer: Ivan Zubarev
Maintainer-email: ivan.zubarev@aalto.fi
License: BSD-3
Platform: any
Classifier: Intended Audience :: Science/Research
Classifier: Intended Audience :: Developers
Classifier: License :: OSI Approved
Classifier: Programming Language :: Python
Classifier: Topic :: Software Development
Classifier: Topic :: Scientific/Engineering
Classifier: Operating System :: Microsoft :: Windows
Classifier: Operating System :: POSIX
Classifier: Operating System :: Unix
Classifier: Operating System :: MacOS
License-File: LICENSE.md
Requires-Dist: numpy
Requires-Dist: scipy
Requires-Dist: mne <=1.7,>=1.0
Requires-Dist: tensorflow <=2.16.1,>=2.12.0
Requires-Dist: matplotlib
